MANIFEST.in
README.rst
setup.py
aliyun_python_sdk_bss_test.egg-info/PKG-INFO
aliyun_python_sdk_bss_test.egg-info/SOURCES.txt
aliyun_python_sdk_bss_test.egg-info/dependency_links.txt
aliyun_python_sdk_bss_test.egg-info/requires.txt
aliyun_python_sdk_bss_test.egg-info/top_level.txt
aliyunsdkbss/__init__.py
aliyunsdkbss/request/__init__.py
aliyunsdkbss/request/v20140714/CreateOrderRequest.py
aliyunsdkbss/request/v20140714/DescribeCashDetailRequest.py
aliyunsdkbss/request/v20140714/DescribeCouponDetailRequest.py
aliyunsdkbss/request/v20140714/DescribeCouponListRequest.py
aliyunsdkbss/request/v20140714/OpenCallbackRequest.py
aliyunsdkbss/request/v20140714/QueryForCssOrderRequest.py
aliyunsdkbss/request/v20140714/SetResourceBusinessStatusRequest.py
aliyunsdkbss/request/v20140714/SubscriptionCreateOrderApiRequest.py
aliyunsdkbss/request/v20140714/VnoBatchRefundOrderRequest.py
aliyunsdkbss/request/v20140714/VnoPayCallBackNotifyRequest.py
aliyunsdkbss/request/v20140714/__init__.py